SenseData/__init__.py
SenseData/client.py
SenseData/dictobj.py
SenseData/stock_pb2.py
SenseData/stock_pb2_grpc.py
sense_client-0.0.1.dist-info/DESCRIPTION.rst
sense_client-0.0.1.dist-info/METADATA
sense_client-0.0.1.dist-info/RECORD
sense_client-0.0.1.dist-info/WHEEL
sense_client-0.0.1.dist-info/metadata.json
sense_client-0.0.1.dist-info/top_level.txt
