Metadata-Version: 2.0
Name: sense-client
Version: 0.0.1
Summary: stock information
Home-page: UNKNOWN
Author: xw20181227
Author-email: weix@sensedeal.ai
License: XW License
Platform: UNKNOWN
Requires-Dist: grpcio
Requires-Dist: grpcio-tools
Requires-Dist: sense-core
Requires-Dist: datetime
